<?xml version="1.0" encoding="utf-8"?><DESADV><Message><Header><DocumentNo>2118000395</DocumentNo><ExternalDocumentNo>FO1802134</ExternalDocumentNo><SupplierGLN>8008530000004</SupplierGLN><ExpectedPickupDate>2018-02-26</ExpectedPickupDate><PlannedDeliveryDate>2018-02-28</PlannedDeliveryDate><VendorShipmentNo /><OrderAddressGLN>8008530000004</OrderAddressGLN><DeliveryAddressGLN>3025570000332</DeliveryAddressGLN></Header><Line><ItemNo>1334-01</ItemNo><VendorItemNo>01005382</VendorItemNo><QuantityBase>3168.000</QuantityBase><GtinBase>4333465053561</GtinBase><QuantityBU>528.000</QuantityBU><GtinBU /><NoOfPallets /><LotNo /><BestBeforeDate>2019-07-15</BestBeforeDate><SerialNo>380085300110569447</SerialNo></Line><Line><ItemNo>2046-01</ItemNo><VendorItemNo>01001737</VendorItemNo><QuantityBase>144.000</QuantityBase><GtinBase>8026924060472</GtinBase><QuantityBU>144.000</QuantityBU><GtinBU /><NoOfPallets /><LotNo /><BestBeforeDate>2018-12-14</BestBeforeDate><SerialNo>380085300027609397</SerialNo></Line><Line><ItemNo>1332-01</ItemNo><VendorItemNo>01005379</VendorItemNo><QuantityBase>5184.000</QuantityBase><GtinBase>4333465053585</GtinBase><QuantityBU>864.000</QuantityBU><GtinBU /><NoOfPallets /><LotNo /><BestBeforeDate>2019-08-12</BestBeforeDate><SerialNo>380085300110608917</SerialNo></Line></Message></DESADV>